resmushit/__init__.py
resmushit/api.py
resmushit/exceptions.py
resmushit/log.py
resmushit/resmushit.py
resmushit/validator.py
resmushit-1.0.1.dist-info/LICENSE
resmushit-1.0.1.dist-info/METADATA
resmushit-1.0.1.dist-info/WHEEL
resmushit-1.0.1.dist-info/top_level.txt
resmushit-1.0.1.dist-info/RECORD
