Metadata-Version: 2.1
Name: resmushit
Version: 1.0.1
Summary: A wrapper for resmush.it API
Home-page: https://resmush.it/
Download-URL: https://github.com/hemansah/resmushit
Author: Hemant Sah
Author-email: hemantsah18@gmail.com
Maintainer: Hemant Sah
License: MIT
Project-URL: Homepage, https://resmush.it/
Project-URL: Documentation, https://github.com/hemansah/resmushit/blob/master/README.md
Project-URL: Repository, https://github.com/hemansah/resmushit/
Classifier: Development Status :: 4 - Beta
Classifier: Intended Audience :: Developers
Classifier: License :: OSI Approved :: MIT License
Classifier: Programming Language :: Python :: 3.12
Classifier: Programming Language :: Python :: 3.11
Classifier: Programming Language :: Python :: 3.10
Classifier: Programming Language :: Python :: 3.9
Classifier: Programming Language :: Python :: 3.8
Classifier: Programming Language :: Python :: 3.7
Classifier: Programming Language :: Python :: 3.6
Classifier: Topic :: Software Development :: Libraries :: Python Modules
Classifier: Topic :: Scientific/Engineering :: Image Processing
Classifier: Topic :: Utilities
Requires-Python: >=3.6,<=3.12
License-File: LICENSE
Requires-Dist: urllib3
Requires-Dist: filetype
